graphalama/__init__.py
graphalama/anim.py
graphalama/buttons.py
graphalama/colors.py
graphalama/constants.py
graphalama/core.py
graphalama/draw.py
graphalama/font.py
graphalama/maths.py
graphalama/shadow.py
graphalama/shapes.py
graphalama/text.py
graphalama/widgets.py
graphalama/data/tick.png
graphalama-0.0.1rc0.dist-info/LICENSE
graphalama-0.0.1rc0.dist-info/METADATA
graphalama-0.0.1rc0.dist-info/WHEEL
graphalama-0.0.1rc0.dist-info/top_level.txt
graphalama-0.0.1rc0.dist-info/RECORD
