Metadata-Version: 2.1
Name: graphalama
Version: 0.0.1rc0
Summary: Easy to use widgets for pygame
Home-page: UNKNOWN
Author: Diego Dorn
Author-email: diego.dorn@free.fr
License: UNKNOWN
Keywords: pygame widget widgets gui llama
Platform: UNKNOWN
Classifier: Development Status :: 3 - Alpha
Classifier: Programming Language :: Python :: 3.5
Classifier: Programming Language :: Python :: 3.6
Requires-Dist: pygame
